PlumHound.py
lib/__init__.py
lib/phCLImanagement.py
lib/phCheckPython.py
lib/phDatabase.py
lib/phDeliver.py
lib/phLoggy.py
lib/phNotifyArgs.py
lib/phTasks.py
modules/AzHound.py
modules/BlueHound.py
modules/__init__.py
modules/ph_ReportIndexer.py
modules/ph_TaskZipper.py
plumhound-1.7.8.data/data/share/plumhound/tasks/BlueHound.tasks
plumhound-1.7.8.data/data/share/plumhound/tasks/Certificates.tasks
plumhound-1.7.8.data/data/share/plumhound/tasks/ConstrainedDelegation.tasks
plumhound-1.7.8.data/data/share/plumhound/tasks/DCSync.tasks
plumhound-1.7.8.data/data/share/plumhound/tasks/DomainUsers.tasks
plumhound-1.7.8.data/data/share/plumhound/tasks/EntraID-AADConnect.tasks
plumhound-1.7.8.data/data/share/plumhound/tasks/EntraID-AttackPaths.tasks
plumhound-1.7.8.data/data/share/plumhound/tasks/EntraID-General.tasks
plumhound-1.7.8.data/data/share/plumhound/tasks/EntraID-MSGraph.tasks
plumhound-1.7.8.data/data/share/plumhound/tasks/EntraID-Principals-ManageID.tasks
plumhound-1.7.8.data/data/share/plumhound/tasks/GPOs.tasks
plumhound-1.7.8.data/data/share/plumhound/tasks/Kerberoasting.tasks
plumhound-1.7.8.data/data/share/plumhound/tasks/broken.tasks
plumhound-1.7.8.data/data/share/plumhound/tasks/default-csv.tasks
plumhound-1.7.8.data/data/share/plumhound/tasks/default-enabledonly.tasks
plumhound-1.7.8.data/data/share/plumhound/tasks/default-faster
plumhound-1.7.8.data/data/share/plumhound/tasks/default.tasks
plumhound-1.7.8.data/data/share/plumhound/tasks/hunt.tasks
plumhound-1.7.8.data/data/share/plumhound/tasks/long.tasks
plumhound-1.7.8.data/data/share/plumhound/tasks/testing.tasks
plumhound-1.7.8.data/data/share/plumhound/template/head.html
plumhound-1.7.8.data/data/share/plumhound/template/html.css
plumhound-1.7.8.data/data/share/plumhound/template/tail.html
plumhound-1.7.8.dist-info/licenses/LICENSE
plumhound-1.7.8.dist-info/METADATA
plumhound-1.7.8.dist-info/WHEEL
plumhound-1.7.8.dist-info/entry_points.txt
plumhound-1.7.8.dist-info/top_level.txt
plumhound-1.7.8.dist-info/RECORD
