Metadata-Version: 2.4
Name: plumhound
Version: 1.7.8
Summary: BloodHoundAD reporting engine for Blue and Purple Teams
Author: PlumHound Team, Kent Ickler, Jordan Drysdale
License:                     GNU GENERAL PUBLIC LICENSE
Project-URL: Homepage, https://github.com/PlumHound/PlumHound
Project-URL: Repository, https://github.com/PlumHound/PlumHound
Project-URL: Issues, https://github.com/PlumHound/PlumHound/issues
Project-URL: Documentation, https://www.blackhillsinfosec.com/plumhound-reporting-engine-for-bloodhoundad/
Keywords: bloodhound,bloodhoundad,plumhound,active-directory,activedirectory,neo4j,blue-team,purple-team,reporting,security
Classifier: Development Status :: 5 - Production/Stable
Classifier: Environment :: Console
Classifier: Intended Audience :: Information Technology
Classifier: Intended Audience :: System Administrators
Classifier: License :: OSI Approved :: GNU General Public License v3 (GPLv3)
Classifier: Programming Language :: Python
Classifier: Programming Language :: Python :: 3
Classifier: Programming Language :: Python :: 3 :: Only
Classifier: Programming Language :: Python :: 3.8
Classifier: Programming Language :: Python :: 3.9
Classifier: Programming Language :: Python :: 3.10
Classifier: Programming Language :: Python :: 3.11
Classifier: Topic :: Security
Classifier: Topic :: System :: Systems Administration
Classifier: Topic :: Utilities
Requires-Python: >=3.8
License-File: LICENSE
Requires-Dist: neo4j
Requires-Dist: py2neo
Requires-Dist: tabulate
Requires-Dist: argcomplete
Requires-Dist: alive-progress
Dynamic: license-file
